{
    "App_1_dep__coll__comp_0CDI.101": "true",
    "App_1_dep__coll__comp_0CDI.102": "true",
    "Cdi_115": "@@Var_2@@@@",
    "Cdi_116": "@@Var_2@@@@",
    "Cdi_117": "@@Var_2@@@@",
    "Cdi_118": "@@Var_2@@@@",
    "Cdi_119": "@@Var_2@@@@",
    "Cdi_120": "@@Var_2@@@@",
    "Cdi_121": "@@Var_2@@@@",
    "Cdi_122": "@@Var_2@@@@",
    "Cdi_123": "@@Var_2@@@@",
    "Cdi_124": "@@Var_2@@@@",
    "Cdi_125": "@@Var_2@@@@",
    "Cdi_126": "@@Var_2@@@@",
    "Cdi_127": "@@Var_2@@@@",
    "Cdi_128": "@@Var_2@@@@",
    "Cdi_129": "@@Var_2@@@@",
    "Cdi_130": "@@Var_2@@@@",
    "Cdi_131": "@@Var_2@@@@",
    "Cdi_132": "@@Var_2@@@@",
    "Cdi_133": "@@Var_2@@@@",
    "Cdi_134": "@@Var_2@@@@",
    "Cdi_135": "@@Var_2@@@@",
    "Cdi_136": "@@Var_2@@@@",
    "Cdi_137": "@@Var_2@@@@",
    "Cdi_138": "@@Var_2@@@@",
    "Cdi_139": "@@Var_2@@@@",
    "Cdi_140": "@@Var_2@@@@",
    "Cdi_141": "@@Var_2@@@@",
    "Cdi_142": "@@Var_2@@@@",
    "Cdi_143": "@@Var_2@@@@",
    "Cdi_144": "@@Var_2@@@@",
    "Cdi_145": "@@Var_2@@@@",
    "Cdi_146": "@@Var_2@@@@",
    "Cdi_147": "@@Var_2@@@@",
    "Cdi_148": "@@Var_2@@@@",
    "Cdi_149": "@@Var_2@@@@",
    "Cdi_150": "@@Var_2@@@@",
    "Cdi_151": "@@Var_2@@@@",
    "Cdi_152": "@@Var_2@@@@",
    "Cdi_153": "@@Var_2@@@@",
    "Cdi_154": "@@Var_2@@@@",
    "Cdi_155": "@@Var_2@@@@",
    "Cdi_156": "@@Var_2@@@@",
    "Cdi_157": "@@Var_2@@@@",
    "Cdi_158": "@@Var_2@@@@",
    "Cdi_159": "@@Var_2@@@@",
    "Cdi_160": "@@Var_2@@@@",
    "Cdi_161": "@@Var_2@@@@",
    "Cdi_162": "@@Var_2@@@@",
    "Cdi_163": "@@Var_2@@@@",
    "Cdi_164": "@@Var_2@@@@",
    "Cdi_165": "@@Var_2@@@@",
    "Cdi_166": "@@Var_2@@@@",
    "Cdi_167": "@@Var_2@@@@",
    "Cdi_168": "@@Var_2@@@@",
    "Cdi_169": "@@Var_2@@@@",
    "Cdi_170": "@@Var_2@@@@",
    "Cdi_171": "@@Var_2@@@@",
    "Cdi_172": "@@Var_2@@@@",
    "Cdi_173": "@@Var_2@@@@",
    "Cdi_174": "@@Var_2@@@@",
    "Cdi_175": "@@Var_2@@@@",
    "Cdi_176": "@@Var_2@@@@",
    "Cdi_177": "@@Var_2@@@@",
    "Cdi_178": "@@Var_2@@@@",
    "Cdi_179": "@@Var_2@@@@",
    "Cdi_180": "@@Var_2@@@@",
    "Cdi_181": "@@Var_2@@@@",
    "Cdi_182": "@@Var_2@@@@",
    "Cdi_183": "@@Var_2@@@@",
    "Cdi_184": "@@Var_2@@@@",
    "Cdi_185": "@@Var_2@@@@",
    "Cdi_186": "@@Var_2@@@@",
    "Cdi_187": "@@Var_2@@@@",
    "Cdi_188": "@@Var_2@@@@",
    "Cdi_189": "@@Var_2@@@@",
    "Cdi_190": "@@Var_2@@@@",
    "Cdi_191": "@@Var_2@@@@",
    "Cdi_192": "@@Var_2@@@@",
    "Cdi_193": "@@Var_2@@@@",
    "Cdi_194": "@@Var_2@@@@",
    "Cdi_195": "@@Var_2@@@@",
    "Cdi_196": "@@Var_2@@@@",
    "Cdi_197": "@@Var_2@@@@",
    "Cdi_198": "@@Var_2@@@@",
    "Cdi_199": "@@Var_2@@@@",
    "Cdi_200": "@@Var_2@@@@"
}
